lunar_times/__init__.py
lunar_times/cli.py
lunar_times-1.0.0.dist-info/METADATA
lunar_times-1.0.0.dist-info/WHEEL
lunar_times-1.0.0.dist-info/entry_points.txt
lunar_times-1.0.0.dist-info/licenses/LICENSE
lunar_times-1.0.0.dist-info/RECORD
