Metadata-Version: 2.4
Name: lunar-times
Version: 1.0.0
Summary: Calculate lunar rise and set times for any location
Project-URL: Homepage, https://github.com/cscortes/lunar-times
Project-URL: Repository, https://github.com/cscortes/lunar-times
Project-URL: Documentation, https://github.com/cscortes/lunar-times/tree/main/docs
Project-URL: Issues, https://github.com/cscortes/lunar-times/issues
Project-URL: Changelog, https://github.com/cscortes/lunar-times/blob/main/docs/CHANGELOG.md
Author-email: Luis Cortés <cscortes@users.noreply.github.com>
Maintainer-email: Luis Cortés <cscortes@users.noreply.github.com>
License: MIT License
License-File: LICENSE
Keywords: astronomy,cli,lunar,moonrise,moonset,times
Classifier: Development Status :: 5 - Production/Stable
Classifier: Environment :: Console
Classifier: Intended Audience :: Developers
Classifier: Intended Audience :: End Users/Desktop
Classifier: License :: OSI Approved :: MIT License
Classifier: Operating System :: OS Independent
Classifier: Programming Language :: Python :: 3
Classifier: Programming Language :: Python :: 3.8
Classifier: Programming Language :: Python :: 3.9
Classifier: Programming Language :: Python :: 3.10
Classifier: Programming Language :: Python :: 3.11
Classifier: Programming Language :: Python :: 3.12
Classifier: Topic :: Scientific/Engineering :: Astronomy
Classifier: Topic :: Utilities
Requires-Python: >=3.8
Requires-Dist: geopy==2.4.1
Requires-Dist: numpy>=1.19.0; python_version < '3.12'
Requires-Dist: numpy>=1.26.0; python_version >= '3.12'
Requires-Dist: pytz==2024.2
Requires-Dist: requests==2.32.4
Requires-Dist: timezonefinder==6.5.4
Provides-Extra: dev
Requires-Dist: docutils==0.20.1; extra == 'dev'
Requires-Dist: flake8==5.0.4; extra == 'dev'
Requires-Dist: mypy==1.14.1; extra == 'dev'
Requires-Dist: pytest-cov==4.0.0; extra == 'dev'
Requires-Dist: pytest==8.3.5; extra == 'dev'
Requires-Dist: python-dotenv==1.0.1; extra == 'dev'
Requires-Dist: twine==6.1.0; extra == 'dev'
Requires-Dist: types-pytz; extra == 'dev'
Requires-Dist: types-requests; extra == 'dev'
